LICENSE
MANIFEST.in
README.md
requirements.txt
setup.py
pspec/__init__.py
pspec/assertions.py
pspec/cli.py
pspec/collectors.py
pspec.egg-info/PKG-INFO
pspec.egg-info/SOURCES.txt
pspec.egg-info/dependency_links.txt
pspec.egg-info/entry_points.txt
pspec.egg-info/requires.txt
pspec.egg-info/top_level.txt
pspec/groups/__init__.py
pspec/groups/base.py
pspec/groups/contextmanager.py
pspec/groups/root.py