Metadata-Version: 1.0
Name: pspec
Version: 0.0.2
Summary: Python testing for humans
Home-page: https://github.com/bfirsh/pspec
Author: Ben Firshman
Author-email: ben@firshman.co.uk
License: UNKNOWN
Platform: UNKNOWN
